drf_jwt_2fa/__init__.py
drf_jwt_2fa/authentication.py
drf_jwt_2fa/exceptions.py
drf_jwt_2fa/sending.py
drf_jwt_2fa/serializers.py
drf_jwt_2fa/settings.py
drf_jwt_2fa/throttling.py
drf_jwt_2fa/token_manager.py
drf_jwt_2fa/urls.py
drf_jwt_2fa/utils.py
drf_jwt_2fa/views.py
drf_jwt_2fa/tests/__init__.py
drf_jwt_2fa/tests/factories.py
drf_jwt_2fa/tests/test_endpoints.py
drf_jwt_2fa/tests/test_throttling.py
drf_jwt_2fa/tests/test_token_manager.py
drf_jwt_2fa/tests/utils.py
drf_jwt_2fa-0.3.0.dist-info/DESCRIPTION.rst
drf_jwt_2fa-0.3.0.dist-info/LICENSE.txt
drf_jwt_2fa-0.3.0.dist-info/METADATA
drf_jwt_2fa-0.3.0.dist-info/RECORD
drf_jwt_2fa-0.3.0.dist-info/WHEEL
drf_jwt_2fa-0.3.0.dist-info/metadata.json
drf_jwt_2fa-0.3.0.dist-info/top_level.txt
