Metadata-Version: 2.0
Name: drf-jwt-2fa
Version: 0.3.0
Summary: Django Rest Framework JWT 2FA
Home-page: https://github.com/suutari/drf-jwt-2fa
Author: Tuomas Suutari
Author-email: tuomas@nepnep.net
License: MIT
Keywords: Authentication,Two Factor,Django Rest Framework,JSON Web Token
Platform: any
Classifier: Development Status :: 4 - Beta
Classifier: Environment :: Web Environment
Classifier: Framework :: Django
Classifier: Framework :: Django :: 1.11
Classifier: Framework :: Django :: 2.0
Classifier: Intended Audience :: Developers
Classifier: License :: OSI Approved :: MIT License
Classifier: Operating System :: OS Independent
Classifier: Programming Language :: Python
Classifier: Programming Language :: Python :: 2
Classifier: Programming Language :: Python :: 2.7
Classifier: Programming Language :: Python :: 3
Classifier: Programming Language :: Python :: 3.4
Classifier: Programming Language :: Python :: 3.5
Classifier: Programming Language :: Python :: 3.6
Classifier: Topic :: Internet :: WWW/HTTP :: Session
Requires-Dist: django (>=1.8)
Requires-Dist: djangorestframework (>=3.0)
Requires-Dist: djangorestframework-jwt (>=1.0)
